GSVA/__init__.py
GSVA/gsva.r
GSVA-1.0.6.dist-info/DESCRIPTION.rst
GSVA-1.0.6.dist-info/METADATA
GSVA-1.0.6.dist-info/RECORD
GSVA-1.0.6.dist-info/WHEEL
GSVA-1.0.6.dist-info/entry_points.txt
GSVA-1.0.6.dist-info/metadata.json
GSVA-1.0.6.dist-info/top_level.txt
