Metadata-Version: 2.0
Name: GSVA
Version: 1.0.6
Summary: Python CLI and module for running the GSVA R bioconductor package with Python Pandas inputs and outputs.
Home-page: https://github.com/jason-weirather/GSVA
Author: Jason L Weirather
Author-email: jason.weirather@gmail.com
License: Apache License, Version 2.0
Keywords: bioinformatics,R,enrichment,GSVA,ssGSEA,GSEA,bioconductor
Platform: UNKNOWN
Classifier: Development Status :: 3 - Alpha
Classifier: Intended Audience :: Science/Research
Classifier: Topic :: Scientific/Engineering :: Bio-Informatics
Classifier: License :: OSI Approved :: Apache Software License
Requires-Dist: pandas
